CLI/App.py
CLI/CLI.py
CLI/__init__.py
CLI_csdummi-1.0.1.dist-info/LICENSE
CLI_csdummi-1.0.1.dist-info/METADATA
CLI_csdummi-1.0.1.dist-info/WHEEL
CLI_csdummi-1.0.1.dist-info/top_level.txt
CLI_csdummi-1.0.1.dist-info/RECORD
