Metadata-Version: 2.1
Name: CLI-csdummi
Version: 1.0.1
Summary: A framework to write CLI projects.
Home-page: https://github.com/csdummi/cli_framework
Author: Joris Gutjahr
Author-email: joris.gutjahr@gmail.com
License: UNKNOWN
Platform: UNKNOWN
Classifier: Programming Language :: Python :: 3
Classifier: License :: OSI Approved :: GNU General Public License v3 (GPLv3)
Classifier: Operating System :: OS Independent
